{
  "format": "traceleak.model_sequence.v1",
  "input": "toy-rsa-like-count-pattern-model-sequence",
  "run_count": 16,
  "public_safe": true,
  "include_counts": true,
  "include_redacted_values": false,
  "label_name": "toy_accept_attempt_bucket",
  "contains_lab_only_labels": true,
  "target": "toy-rsa-like-count-pattern",
  "view": "redacted",
  "notes": [
    "Toy RSA-like count-pattern sample where all records share the same non-zero token set.",
    "The class signal is in candidate_filter loop count ratios, not feature presence.",
    "This is public-safe synthetic telemetry over the toy RSA-like workflow, not real RSA data."
  ],
  "records": [
    {
      "run_id": "toy_count_seq_000001",
      "target": "toy-rsa-like-count-pattern",
      "target_version": "v0",
      "view": "redacted",
      "label": "0",
      "token_counts": {
        "event_type=phase": 1.0,
        "event_type=branch": 2.0,
        "phase=candidate_generation": 1.0,
        "phase=candidate_filter": 6.0,
        "phase=candidate_result": 1.0,
        "context_token=candidate_filter:toy_rsa_like_keygen": 6.0,
        "event_token=branch:candidate_filter:toy_rsa_like_keygen:oddness_check": 1.0,
        "event_token=branch:candidate_result:toy_rsa_like_keygen:candidate_result": 1.0,
        "source_token=examples/toy_rsa_like/target.py:25:toy_rsa_like_keygen:oddness_check": 1.0,
        "source_token=examples/toy_rsa_like/target.py:35:toy_rsa_like_keygen:candidate_result": 1.0,
        "event_type=loop": 6.0,
        "event_token=loop:candidate_filter:toy_rsa_like_keygen:small_divisor_check": 1.0,
        "event_token=loop:candidate_filter:toy_rsa_like_keygen:witness_refine_round": 1.0,
        "event_token=loop:candidate_filter:toy_rsa_like_keygen:acceptance_confirm_round": 5.0,
        "source_token=examples/toy_rsa_like/target.py:29:toy_rsa_like_keygen:small_divisor_check": 1.0
      }
    },
    {
      "run_id": "toy_count_seq_000002",
      "target": "toy-rsa-like-count-pattern",
      "target_version": "v0",
      "view": "redacted",
      "label": "1",
      "token_counts": {
        "event_type=phase": 1.0,
        "event_type=branch": 2.0,
        "phase=candidate_generation": 1.0,
        "phase=candidate_filter": 6.0,
        "phase=candidate_result": 1.0,
        "context_token=candidate_filter:toy_rsa_like_keygen": 6.0,
        "event_token=branch:candidate_filter:toy_rsa_like_keygen:oddness_check": 1.0,
        "event_token=branch:candidate_result:toy_rsa_like_keygen:candidate_result": 1.0,
        "source_token=examples/toy_rsa_like/target.py:25:toy_rsa_like_keygen:oddness_check": 1.0,
        "source_token=examples/toy_rsa_like/target.py:35:toy_rsa_like_keygen:candidate_result": 1.0,
        "event_type=loop": 6.0,
        "event_token=loop:candidate_filter:toy_rsa_like_keygen:small_divisor_check": 1.0,
        "event_token=loop:candidate_filter:toy_rsa_like_keygen:witness_refine_round": 5.0,
        "event_token=loop:candidate_filter:toy_rsa_like_keygen:acceptance_confirm_round": 1.0,
        "source_token=examples/toy_rsa_like/target.py:29:toy_rsa_like_keygen:small_divisor_check": 1.0
      }
    },
    {
      "run_id": "toy_count_seq_000003",
      "target": "toy-rsa-like-count-pattern",
      "target_version": "v0",
      "view": "redacted",
      "label": "0",
      "token_counts": {
        "event_type=phase": 1.0,
        "event_type=branch": 2.0,
        "phase=candidate_generation": 1.0,
        "phase=candidate_filter": 7.0,
        "phase=candidate_result": 1.0,
        "context_token=candidate_filter:toy_rsa_like_keygen": 7.0,
        "event_token=branch:candidate_filter:toy_rsa_like_keygen:oddness_check": 1.0,
        "event_token=branch:candidate_result:toy_rsa_like_keygen:candidate_result": 1.0,
        "source_token=examples/toy_rsa_like/target.py:25:toy_rsa_like_keygen:oddness_check": 1.0,
        "source_token=examples/toy_rsa_like/target.py:35:toy_rsa_like_keygen:candidate_result": 1.0,
        "event_type=loop": 7.0,
        "event_token=loop:candidate_filter:toy_rsa_like_keygen:small_divisor_check": 1.0,
        "event_token=loop:candidate_filter:toy_rsa_like_keygen:witness_refine_round": 2.0,
        "event_token=loop:candidate_filter:toy_rsa_like_keygen:acceptance_confirm_round": 5.0,
        "source_token=examples/toy_rsa_like/target.py:29:toy_rsa_like_keygen:small_divisor_check": 1.0
      }
    },
    {
      "run_id": "toy_count_seq_000004",
      "target": "toy-rsa-like-count-pattern",
      "target_version": "v0",
      "view": "redacted",
      "label": "1",
      "token_counts": {
        "event_type=phase": 1.0,
        "event_type=branch": 2.0,
        "phase=candidate_generation": 1.0,
        "phase=candidate_filter": 7.0,
        "phase=candidate_result": 1.0,
        "context_token=candidate_filter:toy_rsa_like_keygen": 7.0,
        "event_token=branch:candidate_filter:toy_rsa_like_keygen:oddness_check": 1.0,
        "event_token=branch:candidate_result:toy_rsa_like_keygen:candidate_result": 1.0,
        "source_token=examples/toy_rsa_like/target.py:25:toy_rsa_like_keygen:oddness_check": 1.0,
        "source_token=examples/toy_rsa_like/target.py:35:toy_rsa_like_keygen:candidate_result": 1.0,
        "event_type=loop": 7.0,
        "event_token=loop:candidate_filter:toy_rsa_like_keygen:small_divisor_check": 1.0,
        "event_token=loop:candidate_filter:toy_rsa_like_keygen:witness_refine_round": 5.0,
        "event_token=loop:candidate_filter:toy_rsa_like_keygen:acceptance_confirm_round": 2.0,
        "source_token=examples/toy_rsa_like/target.py:29:toy_rsa_like_keygen:small_divisor_check": 1.0
      }
    },
    {
      "run_id": "toy_count_seq_000005",
      "target": "toy-rsa-like-count-pattern",
      "target_version": "v0",
      "view": "redacted",
      "label": "0",
      "token_counts": {
        "event_type=phase": 1.0,
        "event_type=branch": 2.0,
        "phase=candidate_generation": 1.0,
        "phase=candidate_filter": 8.0,
        "phase=candidate_result": 1.0,
        "context_token=candidate_filter:toy_rsa_like_keygen": 8.0,
        "event_token=branch:candidate_filter:toy_rsa_like_keygen:oddness_check": 1.0,
        "event_token=branch:candidate_result:toy_rsa_like_keygen:candidate_result": 1.0,
        "source_token=examples/toy_rsa_like/target.py:25:toy_rsa_like_keygen:oddness_check": 1.0,
        "source_token=examples/toy_rsa_like/target.py:35:toy_rsa_like_keygen:candidate_result": 1.0,
        "event_type=loop": 8.0,
        "event_token=loop:candidate_filter:toy_rsa_like_keygen:small_divisor_check": 1.0,
        "event_token=loop:candidate_filter:toy_rsa_like_keygen:witness_refine_round": 2.0,
        "event_token=loop:candidate_filter:toy_rsa_like_keygen:acceptance_confirm_round": 6.0,
        "source_token=examples/toy_rsa_like/target.py:29:toy_rsa_like_keygen:small_divisor_check": 1.0
      }
    },
    {
      "run_id": "toy_count_seq_000006",
      "target": "toy-rsa-like-count-pattern",
      "target_version": "v0",
      "view": "redacted",
      "label": "1",
      "token_counts": {
        "event_type=phase": 1.0,
        "event_type=branch": 2.0,
        "phase=candidate_generation": 1.0,
        "phase=candidate_filter": 8.0,
        "phase=candidate_result": 1.0,
        "context_token=candidate_filter:toy_rsa_like_keygen": 8.0,
        "event_token=branch:candidate_filter:toy_rsa_like_keygen:oddness_check": 1.0,
        "event_token=branch:candidate_result:toy_rsa_like_keygen:candidate_result": 1.0,
        "source_token=examples/toy_rsa_like/target.py:25:toy_rsa_like_keygen:oddness_check": 1.0,
        "source_token=examples/toy_rsa_like/target.py:35:toy_rsa_like_keygen:candidate_result": 1.0,
        "event_type=loop": 8.0,
        "event_token=loop:candidate_filter:toy_rsa_like_keygen:small_divisor_check": 1.0,
        "event_token=loop:candidate_filter:toy_rsa_like_keygen:witness_refine_round": 6.0,
        "event_token=loop:candidate_filter:toy_rsa_like_keygen:acceptance_confirm_round": 2.0,
        "source_token=examples/toy_rsa_like/target.py:29:toy_rsa_like_keygen:small_divisor_check": 1.0
      }
    },
    {
      "run_id": "toy_count_seq_000007",
      "target": "toy-rsa-like-count-pattern",
      "target_version": "v0",
      "view": "redacted",
      "label": "0",
      "token_counts": {
        "event_type=phase": 1.0,
        "event_type=branch": 2.0,
        "phase=candidate_generation": 1.0,
        "phase=candidate_filter": 9.0,
        "phase=candidate_result": 1.0,
        "context_token=candidate_filter:toy_rsa_like_keygen": 9.0,
        "event_token=branch:candidate_filter:toy_rsa_like_keygen:oddness_check": 1.0,
        "event_token=branch:candidate_result:toy_rsa_like_keygen:candidate_result": 1.0,
        "source_token=examples/toy_rsa_like/target.py:25:toy_rsa_like_keygen:oddness_check": 1.0,
        "source_token=examples/toy_rsa_like/target.py:35:toy_rsa_like_keygen:candidate_result": 1.0,
        "event_type=loop": 9.0,
        "event_token=loop:candidate_filter:toy_rsa_like_keygen:small_divisor_check": 1.0,
        "event_token=loop:candidate_filter:toy_rsa_like_keygen:witness_refine_round": 3.0,
        "event_token=loop:candidate_filter:toy_rsa_like_keygen:acceptance_confirm_round": 6.0,
        "source_token=examples/toy_rsa_like/target.py:29:toy_rsa_like_keygen:small_divisor_check": 1.0
      }
    },
    {
      "run_id": "toy_count_seq_000008",
      "target": "toy-rsa-like-count-pattern",
      "target_version": "v0",
      "view": "redacted",
      "label": "1",
      "token_counts": {
        "event_type=phase": 1.0,
        "event_type=branch": 2.0,
        "phase=candidate_generation": 1.0,
        "phase=candidate_filter": 9.0,
        "phase=candidate_result": 1.0,
        "context_token=candidate_filter:toy_rsa_like_keygen": 9.0,
        "event_token=branch:candidate_filter:toy_rsa_like_keygen:oddness_check": 1.0,
        "event_token=branch:candidate_result:toy_rsa_like_keygen:candidate_result": 1.0,
        "source_token=examples/toy_rsa_like/target.py:25:toy_rsa_like_keygen:oddness_check": 1.0,
        "source_token=examples/toy_rsa_like/target.py:35:toy_rsa_like_keygen:candidate_result": 1.0,
        "event_type=loop": 9.0,
        "event_token=loop:candidate_filter:toy_rsa_like_keygen:small_divisor_check": 1.0,
        "event_token=loop:candidate_filter:toy_rsa_like_keygen:witness_refine_round": 6.0,
        "event_token=loop:candidate_filter:toy_rsa_like_keygen:acceptance_confirm_round": 3.0,
        "source_token=examples/toy_rsa_like/target.py:29:toy_rsa_like_keygen:small_divisor_check": 1.0
      }
    },
    {
      "run_id": "toy_count_seq_000009",
      "target": "toy-rsa-like-count-pattern",
      "target_version": "v0",
      "view": "redacted",
      "label": "0",
      "token_counts": {
        "event_type=phase": 1.0,
        "event_type=branch": 2.0,
        "phase=candidate_generation": 1.0,
        "phase=candidate_filter": 10.0,
        "phase=candidate_result": 1.0,
        "context_token=candidate_filter:toy_rsa_like_keygen": 10.0,
        "event_token=branch:candidate_filter:toy_rsa_like_keygen:oddness_check": 1.0,
        "event_token=branch:candidate_result:toy_rsa_like_keygen:candidate_result": 1.0,
        "source_token=examples/toy_rsa_like/target.py:25:toy_rsa_like_keygen:oddness_check": 1.0,
        "source_token=examples/toy_rsa_like/target.py:35:toy_rsa_like_keygen:candidate_result": 1.0,
        "event_type=loop": 10.0,
        "event_token=loop:candidate_filter:toy_rsa_like_keygen:small_divisor_check": 1.0,
        "event_token=loop:candidate_filter:toy_rsa_like_keygen:witness_refine_round": 3.0,
        "event_token=loop:candidate_filter:toy_rsa_like_keygen:acceptance_confirm_round": 7.0,
        "source_token=examples/toy_rsa_like/target.py:29:toy_rsa_like_keygen:small_divisor_check": 1.0
      }
    },
    {
      "run_id": "toy_count_seq_000010",
      "target": "toy-rsa-like-count-pattern",
      "target_version": "v0",
      "view": "redacted",
      "label": "1",
      "token_counts": {
        "event_type=phase": 1.0,
        "event_type=branch": 2.0,
        "phase=candidate_generation": 1.0,
        "phase=candidate_filter": 10.0,
        "phase=candidate_result": 1.0,
        "context_token=candidate_filter:toy_rsa_like_keygen": 10.0,
        "event_token=branch:candidate_filter:toy_rsa_like_keygen:oddness_check": 1.0,
        "event_token=branch:candidate_result:toy_rsa_like_keygen:candidate_result": 1.0,
        "source_token=examples/toy_rsa_like/target.py:25:toy_rsa_like_keygen:oddness_check": 1.0,
        "source_token=examples/toy_rsa_like/target.py:35:toy_rsa_like_keygen:candidate_result": 1.0,
        "event_type=loop": 10.0,
        "event_token=loop:candidate_filter:toy_rsa_like_keygen:small_divisor_check": 1.0,
        "event_token=loop:candidate_filter:toy_rsa_like_keygen:witness_refine_round": 7.0,
        "event_token=loop:candidate_filter:toy_rsa_like_keygen:acceptance_confirm_round": 3.0,
        "source_token=examples/toy_rsa_like/target.py:29:toy_rsa_like_keygen:small_divisor_check": 1.0
      }
    },
    {
      "run_id": "toy_count_seq_000011",
      "target": "toy-rsa-like-count-pattern",
      "target_version": "v0",
      "view": "redacted",
      "label": "0",
      "token_counts": {
        "event_type=phase": 1.0,
        "event_type=branch": 2.0,
        "phase=candidate_generation": 1.0,
        "phase=candidate_filter": 11.0,
        "phase=candidate_result": 1.0,
        "context_token=candidate_filter:toy_rsa_like_keygen": 11.0,
        "event_token=branch:candidate_filter:toy_rsa_like_keygen:oddness_check": 1.0,
        "event_token=branch:candidate_result:toy_rsa_like_keygen:candidate_result": 1.0,
        "source_token=examples/toy_rsa_like/target.py:25:toy_rsa_like_keygen:oddness_check": 1.0,
        "source_token=examples/toy_rsa_like/target.py:35:toy_rsa_like_keygen:candidate_result": 1.0,
        "event_type=loop": 11.0,
        "event_token=loop:candidate_filter:toy_rsa_like_keygen:small_divisor_check": 1.0,
        "event_token=loop:candidate_filter:toy_rsa_like_keygen:witness_refine_round": 4.0,
        "event_token=loop:candidate_filter:toy_rsa_like_keygen:acceptance_confirm_round": 7.0,
        "source_token=examples/toy_rsa_like/target.py:29:toy_rsa_like_keygen:small_divisor_check": 1.0
      }
    },
    {
      "run_id": "toy_count_seq_000012",
      "target": "toy-rsa-like-count-pattern",
      "target_version": "v0",
      "view": "redacted",
      "label": "1",
      "token_counts": {
        "event_type=phase": 1.0,
        "event_type=branch": 2.0,
        "phase=candidate_generation": 1.0,
        "phase=candidate_filter": 11.0,
        "phase=candidate_result": 1.0,
        "context_token=candidate_filter:toy_rsa_like_keygen": 11.0,
        "event_token=branch:candidate_filter:toy_rsa_like_keygen:oddness_check": 1.0,
        "event_token=branch:candidate_result:toy_rsa_like_keygen:candidate_result": 1.0,
        "source_token=examples/toy_rsa_like/target.py:25:toy_rsa_like_keygen:oddness_check": 1.0,
        "source_token=examples/toy_rsa_like/target.py:35:toy_rsa_like_keygen:candidate_result": 1.0,
        "event_type=loop": 11.0,
        "event_token=loop:candidate_filter:toy_rsa_like_keygen:small_divisor_check": 1.0,
        "event_token=loop:candidate_filter:toy_rsa_like_keygen:witness_refine_round": 7.0,
        "event_token=loop:candidate_filter:toy_rsa_like_keygen:acceptance_confirm_round": 4.0,
        "source_token=examples/toy_rsa_like/target.py:29:toy_rsa_like_keygen:small_divisor_check": 1.0
      }
    },
    {
      "run_id": "toy_count_seq_000013",
      "target": "toy-rsa-like-count-pattern",
      "target_version": "v0",
      "view": "redacted",
      "label": "0",
      "token_counts": {
        "event_type=phase": 1.0,
        "event_type=branch": 2.0,
        "phase=candidate_generation": 1.0,
        "phase=candidate_filter": 12.0,
        "phase=candidate_result": 1.0,
        "context_token=candidate_filter:toy_rsa_like_keygen": 12.0,
        "event_token=branch:candidate_filter:toy_rsa_like_keygen:oddness_check": 1.0,
        "event_token=branch:candidate_result:toy_rsa_like_keygen:candidate_result": 1.0,
        "source_token=examples/toy_rsa_like/target.py:25:toy_rsa_like_keygen:oddness_check": 1.0,
        "source_token=examples/toy_rsa_like/target.py:35:toy_rsa_like_keygen:candidate_result": 1.0,
        "event_type=loop": 12.0,
        "event_token=loop:candidate_filter:toy_rsa_like_keygen:small_divisor_check": 1.0,
        "event_token=loop:candidate_filter:toy_rsa_like_keygen:witness_refine_round": 4.0,
        "event_token=loop:candidate_filter:toy_rsa_like_keygen:acceptance_confirm_round": 8.0,
        "source_token=examples/toy_rsa_like/target.py:29:toy_rsa_like_keygen:small_divisor_check": 1.0
      }
    },
    {
      "run_id": "toy_count_seq_000014",
      "target": "toy-rsa-like-count-pattern",
      "target_version": "v0",
      "view": "redacted",
      "label": "1",
      "token_counts": {
        "event_type=phase": 1.0,
        "event_type=branch": 2.0,
        "phase=candidate_generation": 1.0,
        "phase=candidate_filter": 12.0,
        "phase=candidate_result": 1.0,
        "context_token=candidate_filter:toy_rsa_like_keygen": 12.0,
        "event_token=branch:candidate_filter:toy_rsa_like_keygen:oddness_check": 1.0,
        "event_token=branch:candidate_result:toy_rsa_like_keygen:candidate_result": 1.0,
        "source_token=examples/toy_rsa_like/target.py:25:toy_rsa_like_keygen:oddness_check": 1.0,
        "source_token=examples/toy_rsa_like/target.py:35:toy_rsa_like_keygen:candidate_result": 1.0,
        "event_type=loop": 12.0,
        "event_token=loop:candidate_filter:toy_rsa_like_keygen:small_divisor_check": 1.0,
        "event_token=loop:candidate_filter:toy_rsa_like_keygen:witness_refine_round": 8.0,
        "event_token=loop:candidate_filter:toy_rsa_like_keygen:acceptance_confirm_round": 4.0,
        "source_token=examples/toy_rsa_like/target.py:29:toy_rsa_like_keygen:small_divisor_check": 1.0
      }
    },
    {
      "run_id": "toy_count_seq_000015",
      "target": "toy-rsa-like-count-pattern",
      "target_version": "v0",
      "view": "redacted",
      "label": "0",
      "token_counts": {
        "event_type=phase": 1.0,
        "event_type=branch": 2.0,
        "phase=candidate_generation": 1.0,
        "phase=candidate_filter": 13.0,
        "phase=candidate_result": 1.0,
        "context_token=candidate_filter:toy_rsa_like_keygen": 13.0,
        "event_token=branch:candidate_filter:toy_rsa_like_keygen:oddness_check": 1.0,
        "event_token=branch:candidate_result:toy_rsa_like_keygen:candidate_result": 1.0,
        "source_token=examples/toy_rsa_like/target.py:25:toy_rsa_like_keygen:oddness_check": 1.0,
        "source_token=examples/toy_rsa_like/target.py:35:toy_rsa_like_keygen:candidate_result": 1.0,
        "event_type=loop": 13.0,
        "event_token=loop:candidate_filter:toy_rsa_like_keygen:small_divisor_check": 1.0,
        "event_token=loop:candidate_filter:toy_rsa_like_keygen:witness_refine_round": 5.0,
        "event_token=loop:candidate_filter:toy_rsa_like_keygen:acceptance_confirm_round": 8.0,
        "source_token=examples/toy_rsa_like/target.py:29:toy_rsa_like_keygen:small_divisor_check": 1.0
      }
    },
    {
      "run_id": "toy_count_seq_000016",
      "target": "toy-rsa-like-count-pattern",
      "target_version": "v0",
      "view": "redacted",
      "label": "1",
      "token_counts": {
        "event_type=phase": 1.0,
        "event_type=branch": 2.0,
        "phase=candidate_generation": 1.0,
        "phase=candidate_filter": 13.0,
        "phase=candidate_result": 1.0,
        "context_token=candidate_filter:toy_rsa_like_keygen": 13.0,
        "event_token=branch:candidate_filter:toy_rsa_like_keygen:oddness_check": 1.0,
        "event_token=branch:candidate_result:toy_rsa_like_keygen:candidate_result": 1.0,
        "source_token=examples/toy_rsa_like/target.py:25:toy_rsa_like_keygen:oddness_check": 1.0,
        "source_token=examples/toy_rsa_like/target.py:35:toy_rsa_like_keygen:candidate_result": 1.0,
        "event_type=loop": 13.0,
        "event_token=loop:candidate_filter:toy_rsa_like_keygen:small_divisor_check": 1.0,
        "event_token=loop:candidate_filter:toy_rsa_like_keygen:witness_refine_round": 8.0,
        "event_token=loop:candidate_filter:toy_rsa_like_keygen:acceptance_confirm_round": 5.0,
        "source_token=examples/toy_rsa_like/target.py:29:toy_rsa_like_keygen:small_divisor_check": 1.0
      }
    }
  ]
}
